README.md
setup.py
myntapi/__init__.py
myntapi/noren.py
myntapi/noren_oauth.py
myntapi.egg-info/PKG-INFO
myntapi.egg-info/SOURCES.txt
myntapi.egg-info/dependency_links.txt
myntapi.egg-info/requires.txt
myntapi.egg-info/top_level.txt