Metadata-Version: 2.4
Name: myntapi
Version: 0.0.5
Summary: This PIP package used for Algo traders
Author: zebu
Author-email: it@zebuetrade.com
Classifier: Programming Language :: Python :: 3
Classifier: Operating System :: OS Independent
Requires-Python: >=3.6
Requires-Dist: NorenRestApiPy>=0.0.22
Requires-Dist: requests>=2.31.0
Requires-Dist: websocket_client>=1.6.0
Requires-Dist: pandas>=1.6.0
Requires-Dist: pyyaml>=6.0
Dynamic: author
Dynamic: author-email
Dynamic: classifier
Dynamic: description
Dynamic: description-content-type
Dynamic: requires-dist
Dynamic: requires-python
Dynamic: summary
